xomics_amy_imene/__init__.py
xomics_amy_imene/__main__.py
xomics_amy_imene/annotation.py
xomics_amy_imene/readers_gff.py
xomics_amy_imene-0.2.1.dist-info/METADATA
xomics_amy_imene-0.2.1.dist-info/WHEEL
xomics_amy_imene-0.2.1.dist-info/top_level.txt
xomics_amy_imene-0.2.1.dist-info/RECORD
