Metadata-Version: 2.1
Name: xomics_amy_imene
Version: 0.2.1
Summary: analyse approfondi de fichiers gff
Author-email: Imène Sebaï <imene.sebai@etu.univ-lyon1.fr>, Ndeye Amy Gueye <ndeye.gueye@etu.univ-lyon1.fr>
Project-URL: Repository, http://pedago-service:2325/ngueye/xomics.git
Keywords: python,projet,gestion,packages,dépendances,gene,uniprot
Requires-Python: >=3.8
Requires-Dist: matplotlib >=3.7.5
